geotable/__init__.py
geotable/exceptions.py
geotable/macros.py
geotable/projections.py
geotable-0.4.2.8.dist-info/METADATA
geotable-0.4.2.8.dist-info/WHEEL
geotable-0.4.2.8.dist-info/entry_points.txt
geotable-0.4.2.8.dist-info/top_level.txt
geotable-0.4.2.8.dist-info/RECORD
