Metadata-Version: 2.1
Name: geotable
Version: 0.4.2.8
Summary: Read and write spatial vectors
Home-page: https://github.com/invisibleroads/geotable
Author: Roy Hyunjin Han
Author-email: rhh@crosscompute.com
License: UNKNOWN
Keywords: gdal geos proj4 shapely
Platform: UNKNOWN
Classifier: License :: OSI Approved :: MIT License
Classifier: Operating System :: OS Independent
Classifier: Programming Language :: Python :: 3
Requires-Dist: invisibleroads-macros (>=0.9.5.1)
Requires-Dist: pandas (>=0.20)
Requires-Dist: shapely[vectorized]
Requires-Dist: utm
